Workbook

Sheet Project Info
A1: GlimmoraTeam — Feature Delivery Tracker
A2: Standard program register · Phase 1 MVP
A4: Project name | B4: GlimmoraTeam Global Workforce Platform
A5: Document owner | B5: Product / Engineering
A6: Version | B6: 1.0
A7: Last updated | B7: 46170
A8: Reporting period | B8: Phase 1 (Apr – Aug 2026)
A9: Project manager | B9: [Name]
A10: Engineering manager | B10: [Name]
A11: Status cadence | B11: Weekly — update Assigned To, statuses, and % Complete
A13: Navigation
A14: Sheet | B14: Purpose
A15: Feature Register | B15: Master tracker — edit here
A16: Dashboard | B16: Executive summary (auto-calculated)
A17: Resource Plan | B17: Assignee workload view
A18: Definitions | B18: Column and status definitions

Sheet Feature Register
A1: Feature Register
A2: Single source of truth · Filter by Module, Assigned To, or Overall Status
A11: Feature ID | B11: Module | C11: Feature Name | D11: Description | E11: Priority | F11: Phase | G11: Overall Status | H11: Frontend Status | I11: Backend Status | J11: % Complete | K11: RAG | L11: Assigned To | M11: Accountable (EM) | N11: Planned Start | O11: Planned End | P11: Actual End | Q11: Last Updated | R11: Dependency ID | S11: Remarks
A12: FTR-001 | B12: Platform | C12: Application shell & routing | D12: Multi-portal Next.js App Router with role-based layouts | E12: P1 — Critical | F12: Phase 1 — MVP | G12: Completed | H12: Complete | I12: Complete | J12: =IF(G12="Completed",100,IF(G12="Deferred",0,IF(G12="Cancelled",0,IF(G12="Not Started",0,IF(G12="On Hold",IF(OR(H12="Complete",H12="N/A"),50,25),ROUND((IF(H12="Complete",100,IF(H12="In Progress",50,IF(H12="Blocked",25,0)))+IF(I12="Complete",100,IF(I12="In Progress",50,IF(I12="Blocked",25,IF(I12="N/A",100,0)))))/2,0)))))) | K12: =IF(G12="Completed","Green",IF(G12="Deferred","Grey",IF(G12="Cancelled","Grey",IF(G12="On Hold","Red",IF(J12>=80,"Green",IF(J12>=40,"Amber","Red")))))) | L12: Frontend Lead | M12: Engineering Manager | N12: 46082 | O12: 46142 | Q12: 46170 | R12: — | S12: Production-ready
A13: FTR-002 | B13: Platform | C13: Authentication (email / password) | D13: Login, registration, password reset, session management | E13: P1 — Critical | F13: Phase 1 — MVP | G13: Completed | H13: Complete | I13: Complete | J13: =IF(G13="Completed",100,IF(G13="Deferred",0,IF(G13="Cancelled",0,IF(G13="Not Started",0,IF(G13="On Hold",IF(OR(H13="Complete",H13="N/A"),50,25),ROUND((IF(H13="Complete",100,IF(H13="In Progress",50,IF(H13="Blocked",25,0)))+IF(I13="Complete",100,IF(I13="In Progress",50,IF(I13="Blocked",25,IF(I13="N/A",100,0)))))/2,0)))))) | K13: =IF(G13="Completed","Green",IF(G13="Deferred","Grey",IF(G13="Cancelled","Grey",IF(G13="On Hold","Red",IF(J13>=80,"Green",IF(J13>=40,"Amber","Red")))))) | L13: Backend Lead | M13: Engineering Manager | N13: 46082 | O13: 46127 | Q13: 46170 | R13: FTR-008 | S13: NextAuth v5 + Prisma
A14: FTR-003 | B14: Platform | C14: OAuth (Google & Microsoft) | D14: SSO sign-in for contributors and enterprise users | E14: P1 — Critical | F14: Phase 1 — MVP | G14: In Progress | H14: Complete | I14: In Progress | J14: =IF(G14="Completed",100,IF(G14="Deferred",0,IF(G14="Cancelled",0,IF(G14="Not Started",0,IF(G14="On Hold",IF(OR(H14="Complete",H14="N/A"),50,25),ROUND((IF(H14="Complete",100,IF(H14="In Progress",50,IF(H14="Blocked",25,0)))+IF(I14="Complete",100,IF(I14="In Progress",50,IF(I14="Blocked",25,IF(I14="N/A",100,0)))))/2,0)))))) | K14: =IF(G14="Completed","Green",IF(G14="Deferred","Grey",IF(G14="Cancelled","Grey",IF(G14="On Hold","Red",IF(J14>=80,"Green",IF(J14>=40,"Amber","Red")))))) | L14: Backend Lead | M14: Engineering Manager | N14: 46113 | O14: 46188 | Q14: 46170 | R14: FTR-002 | S14: Enterprise IdP routing partial
A15: FTR-004 | B15: Platform | C15: MFA / TOTP | D15: Multi-factor authentication setup and verification | E15: P2 — High | F15: Phase 1 — Hardening | G15: In Progress | H15: Complete | I15: In Progress | J15: =IF(G15="Completed",100,IF(G15="Deferred",0,IF(G15="Cancelled",0,IF(G15="Not Started",0,IF(G15="On Hold",IF(OR(H15="Complete",H15="N/A"),50,25),ROUND((IF(H15="Complete",100,IF(H15="In Progress",50,IF(H15="Blocked",25,0)))+IF(I15="Complete",100,IF(I15="In Progress",50,IF(I15="Blocked",25,IF(I15="N/A",100,0)))))/2,0)))))) | K15: =IF(G15="Completed","Green",IF(G15="Deferred","Grey",IF(G15="Cancelled","Grey",IF(G15="On Hold","Red",IF(J15>=80,"Green",IF(J15>=40,"Amber","Red")))))) | L15: Security Lead | M15: Engineering Manager | N15: 46143 | O15: 46203 | Q15: 46170 | R15: FTR-002 | S15: E2E coverage pending
A16: FTR-005 | B16: Platform | C16: OTP (email & phone) | D16: One-time password verification flows | E16: P2 — High | F16: Phase 1 — MVP | G16: Completed | H16: Complete | I16: Complete | J16: =IF(G16="Completed",100,IF(G16="Deferred",0,IF(G16="Cancelled",0,IF(G16="Not Started",0,IF(G16="On Hold",IF(OR(H16="Complete",H16="N/A"),50,25),ROUND((IF(H16="Complete",100,IF(H16="In Progress",50,IF(H16="Blocked",25,0)))+IF(I16="Complete",100,IF(I16="In Progress",50,IF(I16="Blocked",25,IF(I16="N/A",100,0)))))/2,0)))))) | K16: =IF(G16="Completed","Green",IF(G16="Deferred","Grey",IF(G16="Cancelled","Grey",IF(G16="On Hold","Red",IF(J16>=80,"Green",IF(J16>=40,"Amber","Red")))))) | L16: Backend Lead | M16: Engineering Manager | N16: 46113 | O16: 46143 | Q16: 46170 | R16: FTR-011 | S16: Live
A17: FTR-006 | B17: Platform | C17: Role-based route guards | D17: Middleware and hooks enforcing portal access | E17: P1 — Critical | F17: Phase 1 — MVP | G17: In Progress | H17: Complete | I17: In Progress | J17: =IF(G17="Completed",100,IF(G17="Deferred",0,IF(G17="Cancelled",0,IF(G17="Not Started",0,IF(G17="On Hold",IF(OR(H17="Complete",H17="N/A"),50,25),ROUND((IF(H17="Complete",100,IF(H17="In Progress",50,IF(H17="Blocked",25,0)))+IF(I17="Complete",100,IF(I17="In Progress",50,IF(I17="Blocked",25,IF(I17="N/A",100,0)))))/2,0)))))) | K17: =IF(G17="Completed","Green",IF(G17="Deferred","Grey",IF(G17="Cancelled","Grey",IF(G17="On Hold","Red",IF(J17>=80,"Green",IF(J17>=40,"Amber","Red")))))) | L17: Platform Lead | M17: Engineering Manager | N17: 46127 | O17: 46174 | Q17: 46170 | R17: FTR-002 | S17: Demo bypass flags in dev
A18: FTR-007 | B18: Platform | C18: API authorization (RBAC audit) | D18: requireRole on all API route handlers | E18: P1 — Critical | F18: Phase 1 — Hardening | G18: In Progress | H18: N/A | I18: In Progress | J18: =IF(G18="Completed",100,IF(G18="Deferred",0,IF(G18="Cancelled",0,IF(G18="Not Started",0,IF(G18="On Hold",IF(OR(H18="Complete",H18="N/A"),50,25),ROUND((IF(H18="Complete",100,IF(H18="In Progress",50,IF(H18="Blocked",25,0)))+IF(I18="Complete",100,IF(I18="In Progress",50,IF(I18="Blocked",25,IF(I18="N/A",100,0)))))/2,0)))))) | K18: =IF(G18="Completed","Green",IF(G18="Deferred","Grey",IF(G18="Cancelled","Grey",IF(G18="On Hold","Red",IF(J18>=80,"Green",IF(J18>=40,"Amber","Red")))))) | L18: Backend Lead | M18: Engineering Manager | N18: 46157 | O18: 46188 | Q18: 46170 | R18: FTR-006 | S18: 2 of 28 routes wired
A19: FTR-008 | B19: Platform | C19: Database schema (Prisma + Postgres) | D19: Core domain models and migrations | E19: P1 — Critical | F19: Phase 1 — MVP | G19: In Progress | H19: N/A | I19: In Progress | J19: =IF(G19="Completed",100,IF(G19="Deferred",0,IF(G19="Cancelled",0,IF(G19="Not Started",0,IF(G19="On Hold",IF(OR(H19="Complete",H19="N/A"),50,25),ROUND((IF(H19="Complete",100,IF(H19="In Progress",50,IF(H19="Blocked",25,0)))+IF(I19="Complete",100,IF(I19="In Progress",50,IF(I19="Blocked",25,IF(I19="N/A",100,0)))))/2,0)))))) | K19: =IF(G19="Completed","Green",IF(G19="Deferred","Grey",IF(G19="Cancelled","Grey",IF(G19="On Hold","Red",IF(J19>=80,"Green",IF(J19>=40,"Amber","Red")))))) | L19: Backend Lead | M19: Engineering Manager | N19: 46096 | O19: 46203 | Q19: 46170 | R19: — | S19: Schema exists; many domains mock-backed
A20: FTR-009 | B20: Platform | C20: Observability (Sentry / logging) | D20: Error tracking, structured logs, alerting | E20: P1 — Critical | F20: Phase 1 — Hardening | G20: Not Started | H20: N/A | I20: Not Started | J20: =IF(G20="Completed",100,IF(G20="Deferred",0,IF(G20="Cancelled",0,IF(G20="Not Started",0,IF(G20="On Hold",IF(OR(H20="Complete",H20="N/A"),50,25),ROUND((IF(H20="Complete",100,IF(H20="In Progress",50,IF(H20="Blocked",25,0)))+IF(I20="Complete",100,IF(I20="In Progress",50,IF(I20="Blocked",25,IF(I20="N/A",100,0)))))/2,0)))))) | K20: =IF(G20="Completed","Green",IF(G20="Deferred","Grey",IF(G20="Cancelled","Grey",IF(G20="On Hold","Red",IF(J20>=80,"Green",IF(J20>=40,"Amber","Red")))))) | L20: DevOps / SRE | M20: Engineering Manager | N20: 46174 | O20: 46218 | Q20: 46170 | R20: — | S20: Production blocker
A21: FTR-010 | B21: Platform | C21: Security headers & CSRF | D21: CSP, rate limiting, CSRF middleware | E21: P1 — Critical | F21: Phase 1 — Hardening | G21: Not Started | H21: N/A | I21: Not Started | J21: =IF(G21="Completed",100,IF(G21="Deferred",0,IF(G21="Cancelled",0,IF(G21="Not Started",0,IF(G21="On Hold",IF(OR(H21="Complete",H21="N/A"),50,25),ROUND((IF(H21="Complete",100,IF(H21="In Progress",50,IF(H21="Blocked",25,0)))+IF(I21="Complete",100,IF(I21="In Progress",50,IF(I21="Blocked",25,IF(I21="N/A",100,0)))))/2,0)))))) | K21: =IF(G21="Completed","Green",IF(G21="Deferred","Grey",IF(G21="Cancelled","Grey",IF(G21="On Hold","Red",IF(J21>=80,"Green",IF(J21>=40,"Amber","Red")))))) | L21: Security Lead | M21: Engineering Manager | N21: 46188 | O21: 46204 | Q21: 46170 | R21: FTR-007
A22: FTR-011 | B22: Platform | C22: Transactional email | D22: Nodemailer + React Email templates | E22: P2 — High | F22: Phase 1 — MVP | G22: In Progress | H22: Complete | I22: In Progress | J22: =IF(G22="Completed",100,IF(G22="Deferred",0,IF(G22="Cancelled",0,IF(G22="Not Started",0,IF(G22="On Hold",IF(OR(H22="Complete",H22="N/A"),50,25),ROUND((IF(H22="Complete",100,IF(H22="In Progress",50,IF(H22="Blocked",25,0)))+IF(I22="Complete",100,IF(I22="In Progress",50,IF(I22="Blocked",25,IF(I22="N/A",100,0)))))/2,0)))))) | K22: =IF(G22="Completed","Green",IF(G22="Deferred","Grey",IF(G22="Cancelled","Grey",IF(G22="On Hold","Red",IF(J22>=80,"Green",IF(J22>=40,"Amber","Red")))))) | L22: Backend Lead | M22: Engineering Manager | N22: 46113 | O22: 46174 | Q22: 46170 | R22: — | S22: Rate limit + RBAC audit pending
A23: FTR-012 | B23: Platform | C23: Razorpay — order creation | D23: Enterprise milestone payment order intent | E23: P1 — Critical | F23: Phase 1 — MVP | G23: Completed | H23: Complete | I23: Complete | J23: =IF(G23="Completed",100,IF(G23="Deferred",0,IF(G23="Cancelled",0,IF(G23="Not Started",0,IF(G23="On Hold",IF(OR(H23="Complete",H23="N/A"),50,25),ROUND((IF(H23="Complete",100,IF(H23="In Progress",50,IF(H23="Blocked",25,0)))+IF(I23="Complete",100,IF(I23="In Progress",50,IF(I23="Blocked",25,IF(I23="N/A",100,0)))))/2,0)))))) | K23: =IF(G23="Completed","Green",IF(G23="Deferred","Grey",IF(G23="Cancelled","Grey",IF(G23="On Hold","Red",IF(J23>=80,"Green",IF(J23>=40,"Amber","Red")))))) | L23: Backend Lead | M23: Engineering Manager | N23: 46113 | O23: 46157 | Q23: 46170 | R23: FTR-048 | S23: Gated by acceptance decision
A24: FTR-013 | B24: Platform | C24: Razorpay — webhooks | D24: HMAC signature verification, idempotent events | E24: P1 — Critical | F24: Phase 1 — MVP | G24: Completed | H24: N/A | I24: Complete | J24: =IF(G24="Completed",100,IF(G24="Deferred",0,IF(G24="Cancelled",0,IF(G24="Not Started",0,IF(G24="On Hold",IF(OR(H24="Complete",H24="N/A"),50,25),ROUND((IF(H24="Complete",100,IF(H24="In Progress",50,IF(H24="Blocked",25,0)))+IF(I24="Complete",100,IF(I24="In Progress",50,IF(I24="Blocked",25,IF(I24="N/A",100,0)))))/2,0)))))) | K24: =IF(G24="Completed","Green",IF(G24="Deferred","Grey",IF(G24="Cancelled","Grey",IF(G24="On Hold","Red",IF(J24>=80,"Green",IF(J24>=40,"Amber","Red")))))) | L24: Backend Lead | M24: Engineering Manager | N24: 46127 | O24: 46157 | Q24: 46170 | R24: FTR-012 | S24: Shipped
A25: FTR-014 | B25: Platform | C25: Razorpay — payouts | D25: Platform to contributor payout leg | E25: P2 — High | F25: Phase 1 — Hardening | G25: Not Started | H25: In Progress | I25: Not Started | J25: =IF(G25="Completed",100,IF(G25="Deferred",0,IF(G25="Cancelled",0,IF(G25="Not Started",0,IF(G25="On Hold",IF(OR(H25="Complete",H25="N/A"),50,25),ROUND((IF(H25="Complete",100,IF(H25="In Progress",50,IF(H25="Blocked",25,0)))+IF(I25="Complete",100,IF(I25="In Progress",50,IF(I25="Blocked",25,IF(I25="N/A",100,0)))))/2,0)))))) | K25: =IF(G25="Completed","Green",IF(G25="Deferred","Grey",IF(G25="Cancelled","Grey",IF(G25="On Hold","Red",IF(J25>=80,"Green",IF(J25>=40,"Amber","Red")))))) | L25: Backend Lead | M25: Engineering Manager | N25: 46204 | O25: 46233 | Q25: 46170 | R25: FTR-012 | S25: Conditional on payout go-live
A26: FTR-015 | B26: Platform | C26: Audit log | D26: Immutable audit trail for state changes | E26: P1 — Critical | F26: Phase 1 — MVP | G26: In Progress | H26: Complete | I26: In Progress | J26: =IF(G26="Completed",100,IF(G26="Deferred",0,IF(G26="Cancelled",0,IF(G26="Not Started",0,IF(G26="On Hold",IF(OR(H26="Complete",H26="N/A"),50,25),ROUND((IF(H26="Complete",100,IF(H26="In Progress",50,IF(H26="Blocked",25,0)))+IF(I26="Complete",100,IF(I26="In Progress",50,IF(I26="Blocked",25,IF(I26="N/A",100,0)))))/2,0)))))) | K26: =IF(G26="Completed","Green",IF(G26="Deferred","Grey",IF(G26="Cancelled","Grey",IF(G26="On Hold","Red",IF(J26>=80,"Green",IF(J26>=40,"Amber","Red")))))) | L26: Backend Lead | M26: Engineering Manager | N26: 46113 | O26: 46188 | Q26: 46170 | R26: FTR-008 | S26: Acceptance decisions persisted
A27: FTR-016 | B27: Platform | C27: Subscription & plan gating | D27: SaaS plan limits, usage, feature gates | E27: P2 — High | F27: Phase 1 — MVP | G27: In Progress | H27: Complete | I27: In Progress | J27: =IF(G27="Completed",100,IF(G27="Deferred",0,IF(G27="Cancelled",0,IF(G27="Not Started",0,IF(G27="On Hold",IF(OR(H27="Complete",H27="N/A"),50,25),ROUND((IF(H27="Complete",100,IF(H27="In Progress",50,IF(H27="Blocked",25,0)))+IF(I27="Complete",100,IF(I27="In Progress",50,IF(I27="Blocked",25,IF(I27="N/A",100,0)))))/2,0)))))) | K27: =IF(G27="Completed","Green",IF(G27="Deferred","Grey",IF(G27="Cancelled","Grey",IF(G27="On Hold","Red",IF(J27>=80,"Green",IF(J27>=40,"Amber","Red")))))) | L27: Full Stack Developer | M27: Engineering Manager | N27: 46143 | O27: 46170 | Q27: 46170 | R27: FTR-008 | S27: Sidebar plan chip shipped
A28: FTR-017 | B28: Platform | C28: Backend API handoff | D28: External backend team scaffold + contract | E28: P2 — High | F28: Phase 1 — MVP | G28: In Progress | H28: Complete | I28: In Progress | J28: =IF(G28="Completed",100,IF(G28="Deferred",0,IF(G28="Cancelled",0,IF(G28="Not Started",0,IF(G28="On Hold",IF(OR(H28="Complete",H28="N/A"),50,25),ROUND((IF(H28="Complete",100,IF(H28="In Progress",50,IF(H28="Blocked",25,0)))+IF(I28="Complete",100,IF(I28="In Progress",50,IF(I28="Blocked",25,IF(I28="N/A",100,0)))))/2,0)))))) | K28: =IF(G28="Completed","Green",IF(G28="Deferred","Grey",IF(G28="Cancelled","Grey",IF(G28="On Hold","Red",IF(J28>=80,"Green",IF(J28>=40,"Amber","Red")))))) | L28: Engineering Manager | M28: Engineering Manager | N28: 46143 | O28: 46170 | Q28: 46170 | R28: — | S28: Frontend owns Prisma
A29: FTR-020 | B29: Contributor | C29: Dashboard | D29: Contributor home — tasks, progress, alerts | E29: P1 — Critical | F29: Phase 1 — MVP | G29: In Progress | H29: Complete | I29: In Progress | J29: =IF(G29="Completed",100,IF(G29="Deferred",0,IF(G29="Cancelled",0,IF(G29="Not Started",0,IF(G29="On Hold",IF(OR(H29="Complete",H29="N/A"),50,25),ROUND((IF(H29="Complete",100,IF(H29="In Progress",50,IF(H29="Blocked",25,0)))+IF(I29="Complete",100,IF(I29="In Progress",50,IF(I29="Blocked",25,IF(I29="N/A",100,0)))))/2,0)))))) | K29: =IF(G29="Completed","Green",IF(G29="Deferred","Grey",IF(G29="Cancelled","Grey",IF(G29="On Hold","Red",IF(J29>=80,"Green",IF(J29>=40,"Amber","Red")))))) | L29: Frontend Lead | M29: Engineering Manager | N29: 46113 | O29: 46143 | Q29: 46170 | R29: FTR-021 | S29: Mock / seed data
A30: FTR-021 | B30: Contributor | C30: Task workroom & lifecycle | D30: Assigned → submit → review → approved flow | E30: P1 — Critical | F30: Phase 1 — MVP | G30: In Progress | H30: Complete | I30: In Progress | J30: =IF(G30="Completed",100,IF(G30="Deferred",0,IF(G30="Cancelled",0,IF(G30="Not Started",0,IF(G30="On Hold",IF(OR(H30="Complete",H30="N/A"),50,25),ROUND((IF(H30="Complete",100,IF(H30="In Progress",50,IF(H30="Blocked",25,0)))+IF(I30="Complete",100,IF(I30="In Progress",50,IF(I30="Blocked",25,IF(I30="N/A",100,0)))))/2,0)))))) | K30: =IF(G30="Completed","Green",IF(G30="Deferred","Grey",IF(G30="Cancelled","Grey",IF(G30="On Hold","Red",IF(J30>=80,"Green",IF(J30>=40,"Amber","Red")))))) | L30: Full Stack Developer | M30: Engineering Manager | N30: 46127 | O30: 46203 | Q30: 46170 | R30: FTR-090 | S30: localStorage today
A31: FTR-022 | B31: Contributor | C31: Submissions & revisions | D31: Deliverable submit and rework loop | E31: P1 — Critical | F31: Phase 1 — MVP | G31: In Progress | H31: Complete | I31: In Progress | J31: =IF(G31="Completed",100,IF(G31="Deferred",0,IF(G31="Cancelled",0,IF(G31="Not Started",0,IF(G31="On Hold",IF(OR(H31="Complete",H31="N/A"),50,25),ROUND((IF(H31="Complete",100,IF(H31="In Progress",50,IF(H31="Blocked",25,0)))+IF(I31="Complete",100,IF(I31="In Progress",50,IF(I31="Blocked",25,IF(I31="N/A",100,0)))))/2,0)))))) | K31: =IF(G31="Completed","Green",IF(G31="Deferred","Grey",IF(G31="Cancelled","Grey",IF(G31="On Hold","Red",IF(J31>=80,"Green",IF(J31>=40,"Amber","Red")))))) | L31: Full Stack Developer | M31: Engineering Manager | N31: 46127 | O31: 46203 | Q31: 46170 | R31: FTR-021
A32: FTR-023 | B32: Contributor | C32: Digital twin profile | D32: Skills, evidence, portfolio | E32: P2 — High | F32: Phase 1 — MVP | G32: In Progress | H32: Complete | I32: In Progress | J32: =IF(G32="Completed",100,IF(G32="Deferred",0,IF(G32="Cancelled",0,IF(G32="Not Started",0,IF(G32="On Hold",IF(OR(H32="Complete",H32="N/A"),50,25),ROUND((IF(H32="Complete",100,IF(H32="In Progress",50,IF(H32="Blocked",25,0)))+IF(I32="Complete",100,IF(I32="In Progress",50,IF(I32="Blocked",25,IF(I32="N/A",100,0)))))/2,0)))))) | K32: =IF(G32="Completed","Green",IF(G32="Deferred","Grey",IF(G32="Cancelled","Grey",IF(G32="On Hold","Red",IF(J32>=80,"Green",IF(J32>=40,"Amber","Red")))))) | L32: Full Stack Developer | M32: Engineering Manager | N32: 46113 | O32: 46188 | Q32: 46170 | R32: —
A33: FTR-024 | B33: Contributor | C33: Onboarding flow | D33: Multi-step contributor registration | E33: P1 — Critical | F33: Phase 1 — MVP | G33: In Progress | H33: Complete | I33: In Progress | J33: =IF(G33="Completed",100,IF(G33="Deferred",0,IF(G33="Cancelled",0,IF(G33="Not Started",0,IF(G33="On Hold",IF(OR(H33="Complete",H33="N/A"),50,25),ROUND((IF(H33="Complete",100,IF(H33="In Progress",50,IF(H33="Blocked",25,0)))+IF(I33="Complete",100,IF(I33="In Progress",50,IF(I33="Blocked",25,IF(I33="N/A",100,0)))))/2,0)))))) | K33: =IF(G33="Completed","Green",IF(G33="Deferred","Grey",IF(G33="Cancelled","Grey",IF(G33="On Hold","Red",IF(J33>=80,"Green",IF(J33>=40,"Amber","Red")))))) | L33: Full Stack Developer | M33: Engineering Manager | N33: 46113 | O33: 46174 | Q33: 46170 | R33: FTR-002
A34: FTR-025 | B34: Contributor | C34: Earnings & payouts view | D34: Contributor earnings dashboard | E34: P2 — High | F34: Phase 1 — Hardening | G34: In Progress | H34: Complete | I34: Not Started | J34: =IF(G34="Completed",100,IF(G34="Deferred",0,IF(G34="Cancelled",0,IF(G34="Not Started",0,IF(G34="On Hold",IF(OR(H34="Complete",H34="N/A"),50,25),ROUND((IF(H34="Complete",100,IF(H34="In Progress",50,IF(H34="Blocked",25,0)))+IF(I34="Complete",100,IF(I34="In Progress",50,IF(I34="Blocked",25,IF(I34="N/A",100,0)))))/2,0)))))) | K34: =IF(G34="Completed","Green",IF(G34="Deferred","Grey",IF(G34="Cancelled","Grey",IF(G34="On Hold","Red",IF(J34>=80,"Green",IF(J34>=40,"Amber","Red")))))) | L34: Frontend Lead | M34: Engineering Manager | N34: 46174 | O34: 46218 | Q34: 46170 | R34: FTR-014 | S34: Mock data
A35: FTR-026 | B35: Contributor | C35: Credentials wallet | D35: Issue, share, verify credentials | E35: P2 — High | F35: Phase 1 — MVP | G35: In Progress | H35: Complete | I35: In Progress | J35: =IF(G35="Completed",100,IF(G35="Deferred",0,IF(G35="Cancelled",0,IF(G35="Not Started",0,IF(G35="On Hold",IF(OR(H35="Complete",H35="N/A"),50,25),ROUND((IF(H35="Complete",100,IF(H35="In Progress",50,IF(H35="Blocked",25,0)))+IF(I35="Complete",100,IF(I35="In Progress",50,IF(I35="Blocked",25,IF(I35="N/A",100,0)))))/2,0)))))) | K35: =IF(G35="Completed","Green",IF(G35="Deferred","Grey",IF(G35="Cancelled","Grey",IF(G35="On Hold","Red",IF(J35>=80,"Green",IF(J35>=40,"Amber","Red")))))) | L35: Full Stack Developer | M35: Engineering Manager | N35: 46143 | O35: 46203 | Q35: 46170 | R35: — | S35: Public share page works
A36: FTR-027 | B36: Contributor | C36: Support & tickets | D36: FAQs, grievances, safety reports | E36: P3 — Medium | F36: Phase 1 — MVP | G36: In Progress | H36: Complete | I36: In Progress | J36: =IF(G36="Completed",100,IF(G36="Deferred",0,IF(G36="Cancelled",0,IF(G36="Not Started",0,IF(G36="On Hold",IF(OR(H36="Complete",H36="N/A"),50,25),ROUND((IF(H36="Complete",100,IF(H36="In Progress",50,IF(H36="Blocked",25,0)))+IF(I36="Complete",100,IF(I36="In Progress",50,IF(I36="Blocked",25,IF(I36="N/A",100,0)))))/2,0)))))) | K36: =IF(G36="Completed","Green",IF(G36="Deferred","Grey",IF(G36="Cancelled","Grey",IF(G36="On Hold","Red",IF(J36>=80,"Green",IF(J36>=40,"Amber","Red")))))) | L36: Full Stack Developer | M36: Engineering Manager | N36: 46143 | O36: 46204 | Q36: 46170 | R36: —
A37: FTR-028 | B37: Contributor | C37: Community & messages | D37: Community feed and messaging | E37: P3 — Medium | F37: Phase 2 | G37: Deferred | H37: Complete | I37: Not Started | J37: =IF(G37="Completed",100,IF(G37="Deferred",0,IF(G37="Cancelled",0,IF(G37="Not Started",0,IF(G37="On Hold",IF(OR(H37="Complete",H37="N/A"),50,25),ROUND((IF(H37="Complete",100,IF(H37="In Progress",50,IF(H37="Blocked",25,0)))+IF(I37="Complete",100,IF(I37="In Progress",50,IF(I37="Blocked",25,IF(I37="N/A",100,0)))))/2,0)))))) | K37: =IF(G37="Completed","Green",IF(G37="Deferred","Grey",IF(G37="Cancelled","Grey",IF(G37="On Hold","Red",IF(J37>=80,"Green",IF(J37>=40,"Amber","Red")))))) | L37: Frontend Lead | M37: Engineering Manager | N37: 46204 | O37: 46235 | Q37: 46170 | R37: — | S37: Visual-only mock
A38: FTR-029 | B38: Contributor | C38: Learning recommendations | D38: AI skill learning suggestions | E38: P3 — Medium | F38: Phase 2 | G38: Deferred | H38: Complete | I38: Not Started | J38: =IF(G38="Completed",100,IF(G38="Deferred",0,IF(G38="Cancelled",0,IF(G38="Not Started",0,IF(G38="On Hold",IF(OR(H38="Complete",H38="N/A"),50,25),ROUND((IF(H38="Complete",100,IF(H38="In Progress",50,IF(H38="Blocked",25,0)))+IF(I38="Complete",100,IF(I38="In Progress",50,IF(I38="Blocked",25,IF(I38="N/A",100,0)))))/2,0)))))) | K38: =IF(G38="Completed","Green",IF(G38="Deferred","Grey",IF(G38="Cancelled","Grey",IF(G38="On Hold","Red",IF(J38>=80,"Green",IF(J38>=40,"Amber","Red")))))) | L38: Frontend Lead | M38: Engineering Manager | N38: 46204 | O38: 46235 | Q38: 46170 | R38: FTR-097
A39: FTR-030 | B39: Contributor | C39: Account auth settings | D39: Password / OAuth / SSO mode selection | E39: P2 — High | F39: Phase 1 — MVP | G39: In Progress | H39: Complete | I39: In Progress | J39: =IF(G39="Completed",100,IF(G39="Deferred",0,IF(G39="Cancelled",0,IF(G39="Not Started",0,IF(G39="On Hold",IF(OR(H39="Complete",H39="N/A"),50,25),ROUND((IF(H39="Complete",100,IF(H39="In Progress",50,IF(H39="Blocked",25,0)))+IF(I39="Complete",100,IF(I39="In Progress",50,IF(I39="Blocked",25,IF(I39="N/A",100,0)))))/2,0)))))) | K39: =IF(G39="Completed","Green",IF(G39="Deferred","Grey",IF(G39="Cancelled","Grey",IF(G39="On Hold","Red",IF(J39>=80,"Green",IF(J39>=40,"Amber","Red")))))) | L39: Full Stack Developer | M39: Engineering Manager | N39: 46143 | O39: 46170 | Q39: 46170 | R39: FTR-003 | S39: Recently shipped
A40: FTR-040 | B40: Enterprise | C40: Dashboard | D40: Executive dashboard with KPIs and plan usage | E40: P1 — Critical | F40: Phase 1 — MVP | G40: In Progress | H40: Complete | I40: In Progress | J40: =IF(G40="Completed",100,IF(G40="Deferred",0,IF(G40="Cancelled",0,IF(G40="Not Started",0,IF(G40="On Hold",IF(OR(H40="Complete",H40="N/A"),50,25),ROUND((IF(H40="Complete",100,IF(H40="In Progress",50,IF(H40="Blocked",25,0)))+IF(I40="Complete",100,IF(I40="In Progress",50,IF(I40="Blocked",25,IF(I40="N/A",100,0)))))/2,0)))))) | K40: =IF(G40="Completed","Green",IF(G40="Deferred","Grey",IF(G40="Cancelled","Grey",IF(G40="On Hold","Red",IF(J40>=80,"Green",IF(J40>=40,"Amber","Red")))))) | L40: Frontend Lead | M40: Engineering Manager | N40: 46113 | O40: 46143 | Q40: 46170 | R40: FTR-016
A41: FTR-041 | B41: Enterprise | C41: SOW repository | D41: SOW list and detail views | E41: P1 — Critical | F41: Phase 1 — MVP | G41: In Progress | H41: Complete | I41: In Progress | J41: =IF(G41="Completed",100,IF(G41="Deferred",0,IF(G41="Cancelled",0,IF(G41="Not Started",0,IF(G41="On Hold",IF(OR(H41="Complete",H41="N/A"),50,25),ROUND((IF(H41="Complete",100,IF(H41="In Progress",50,IF(H41="Blocked",25,0)))+IF(I41="Complete",100,IF(I41="In Progress",50,IF(I41="Blocked",25,IF(I41="N/A",100,0)))))/2,0)))))) | K41: =IF(G41="Completed","Green",IF(G41="Deferred","Grey",IF(G41="Cancelled","Grey",IF(G41="On Hold","Red",IF(J41>=80,"Green",IF(J41>=40,"Amber","Red")))))) | L41: Full Stack Developer | M41: Engineering Manager | N41: 46113 | O41: 46188 | Q41: 46170 | R41: FTR-091 | S41: API + mocks hybrid
A42: FTR-042 | B42: Enterprise | C42: SOW intake (upload + AI) | D42: 5-stage intake wizard with AI extraction | E42: P1 — Critical | F42: Phase 1 — MVP | G42: In Progress | H42: Complete | I42: In Progress | J42: =IF(G42="Completed",100,IF(G42="Deferred",0,IF(G42="Cancelled",0,IF(G42="Not Started",0,IF(G42="On Hold",IF(OR(H42="Complete",H42="N/A"),50,25),ROUND((IF(H42="Complete",100,IF(H42="In Progress",50,IF(H42="Blocked",25,0)))+IF(I42="Complete",100,IF(I42="In Progress",50,IF(I42="Blocked",25,IF(I42="N/A",100,0)))))/2,0)))))) | K42: =IF(G42="Completed","Green",IF(G42="Deferred","Grey",IF(G42="Cancelled","Grey",IF(G42="On Hold","Red",IF(J42>=80,"Green",IF(J42>=40,"Amber","Red")))))) | L42: Full Stack Developer | M42: Engineering Manager | N42: 46127 | O42: 46203 | Q42: 46170 | R42: FTR-097 | S42: Commit local-state
A43: FTR-043 | B43: Enterprise | C43: SOW approval pipeline | D43: 5-stage commercial / legal sign-off | E43: P1 — Critical | F43: Phase 1 — MVP | G43: In Progress | H43: Complete | I43: In Progress | J43: =IF(G43="Completed",100,IF(G43="Deferred",0,IF(G43="Cancelled",0,IF(G43="Not Started",0,IF(G43="On Hold",IF(OR(H43="Complete",H43="N/A"),50,25),ROUND((IF(H43="Complete",100,IF(H43="In Progress",50,IF(H43="Blocked",25,0)))+IF(I43="Complete",100,IF(I43="In Progress",50,IF(I43="Blocked",25,IF(I43="N/A",100,0)))))/2,0)))))) | K43: =IF(G43="Completed","Green",IF(G43="Deferred","Grey",IF(G43="Cancelled","Grey",IF(G43="On Hold","Red",IF(J43>=80,"Green",IF(J43>=40,"Amber","Red")))))) | L43: Full Stack Developer | M43: Engineering Manager | N43: 46127 | O43: 46203 | Q43: 46170 | R43: FTR-041
A44: FTR-044 | B44: Enterprise | C44: Decomposition workspace | D44: Break SOW into workstreams and tasks | E44: P1 — Critical | F44: Phase 1 — MVP | G44: In Progress | H44: Complete | I44: Not Started | J44: =IF(G44="Completed",100,IF(G44="Deferred",0,IF(G44="Cancelled",0,IF(G44="Not Started",0,IF(G44="On Hold",IF(OR(H44="Complete",H44="N/A"),50,25),ROUND((IF(H44="Complete",100,IF(H44="In Progress",50,IF(H44="Blocked",25,0)))+IF(I44="Complete",100,IF(I44="In Progress",50,IF(I44="Blocked",25,IF(I44="N/A",100,0)))))/2,0)))))) | K44: =IF(G44="Completed","Green",IF(G44="Deferred","Grey",IF(G44="Cancelled","Grey",IF(G44="On Hold","Red",IF(J44>=80,"Green",IF(J44>=40,"Amber","Red")))))) | L44: Full Stack Developer | M44: Engineering Manager | N44: 46143 | O44: 46204 | Q44: 46170 | R44: FTR-091 | S44: Mock plans
A45: FTR-045 | B45: Enterprise | C45: Team matching & formation | D45: Suggest and assign contributors | E45: P2 — High | F45: Phase 1 — MVP | G45: In Progress | H45: Complete | I45: Not Started | J45: =IF(G45="Completed",100,IF(G45="Deferred",0,IF(G45="Cancelled",0,IF(G45="Not Started",0,IF(G45="On Hold",IF(OR(H45="Complete",H45="N/A"),50,25),ROUND((IF(H45="Complete",100,IF(H45="In Progress",50,IF(H45="Blocked",25,0)))+IF(I45="Complete",100,IF(I45="In Progress",50,IF(I45="Blocked",25,IF(I45="N/A",100,0)))))/2,0)))))) | K45: =IF(G45="Completed","Green",IF(G45="Deferred","Grey",IF(G45="Cancelled","Grey",IF(G45="On Hold","Red",IF(J45>=80,"Green",IF(J45>=40,"Amber","Red")))))) | L45: Frontend Lead | M45: Engineering Manager | N45: 46157 | O45: 46218 | Q45: 46170 | R45: FTR-044
A46: FTR-046 | B46: Enterprise | C46: Projects portfolio | D46: Active and completed project tiles | E46: P1 — Critical | F46: Phase 1 — MVP | G46: In Progress | H46: Complete | I46: Not Started | J46: =IF(G46="Completed",100,IF(G46="Deferred",0,IF(G46="Cancelled",0,IF(G46="Not Started",0,IF(G46="On Hold",IF(OR(H46="Complete",H46="N/A"),50,25),ROUND((IF(H46="Complete",100,IF(H46="In Progress",50,IF(H46="Blocked",25,0)))+IF(I46="Complete",100,IF(I46="In Progress",50,IF(I46="Blocked",25,IF(I46="N/A",100,0)))))/2,0)))))) | K46: =IF(G46="Completed","Green",IF(G46="Deferred","Grey",IF(G46="Cancelled","Grey",IF(G46="On Hold","Red",IF(J46>=80,"Green",IF(J46>=40,"Amber","Red")))))) | L46: Full Stack Developer | M46: Engineering Manager | N46: 46143 | O46: 46204 | Q46: 46170 | R46: FTR-091
A47: FTR-047 | B47: Enterprise | C47: Delivery tracking | D47: Milestones, exceptions, lifecycle view | E47: P1 — Critical | F47: Phase 1 — MVP | G47: In Progress | H47: Complete | I47: Not Started | J47: =IF(G47="Completed",100,IF(G47="Deferred",0,IF(G47="Cancelled",0,IF(G47="Not Started",0,IF(G47="On Hold",IF(OR(H47="Complete",H47="N/A"),50,25),ROUND((IF(H47="Complete",100,IF(H47="In Progress",50,IF(H47="Blocked",25,0)))+IF(I47="Complete",100,IF(I47="In Progress",50,IF(I47="Blocked",25,IF(I47="N/A",100,0)))))/2,0)))))) | K47: =IF(G47="Completed","Green",IF(G47="Deferred","Grey",IF(G47="Cancelled","Grey",IF(G47="On Hold","Red",IF(J47>=80,"Green",IF(J47>=40,"Amber","Red")))))) | L47: Full Stack Developer | M47: Engineering Manager | N47: 46143 | O47: 46204 | Q47: 46170 | R47: FTR-021
A48: FTR-048 | B48: Enterprise | C48: Review & acceptance queue | D48: Accept / rework deliverables | E48: P1 — Critical | F48: Phase 1 — MVP | G48: In Progress | H48: Complete | I48: In Progress | J48: =IF(G48="Completed",100,IF(G48="Deferred",0,IF(G48="Cancelled",0,IF(G48="Not Started",0,IF(G48="On Hold",IF(OR(H48="Complete",H48="N/A"),50,25),ROUND((IF(H48="Complete",100,IF(H48="In Progress",50,IF(H48="Blocked",25,0)))+IF(I48="Complete",100,IF(I48="In Progress",50,IF(I48="Blocked",25,IF(I48="N/A",100,0)))))/2,0)))))) | K48: =IF(G48="Completed","Green",IF(G48="Deferred","Grey",IF(G48="Cancelled","Grey",IF(G48="On Hold","Red",IF(J48>=80,"Green",IF(J48>=40,"Amber","Red")))))) | L48: Full Stack Developer | M48: Engineering Manager | N48: 46127 | O48: 46174 | Q48: 46170 | R48: FTR-015 | S48: Postgres audit log
A49: FTR-049 | B49: Enterprise | C49: Reviewer sub-portal | D49: QA inbox, task monitor, metrics | E49: P2 — High | F49: Phase 1 — MVP | G49: In Progress | H49: Complete | I49: Not Started | J49: =IF(G49="Completed",100,IF(G49="Deferred",0,IF(G49="Cancelled",0,IF(G49="Not Started",0,IF(G49="On Hold",IF(OR(H49="Complete",H49="N/A"),50,25),ROUND((IF(H49="Complete",100,IF(H49="In Progress",50,IF(H49="Blocked",25,0)))+IF(I49="Complete",100,IF(I49="In Progress",50,IF(I49="Blocked",25,IF(I49="N/A",100,0)))))/2,0)))))) | K49: =IF(G49="Completed","Green",IF(G49="Deferred","Grey",IF(G49="Cancelled","Grey",IF(G49="On Hold","Red",IF(J49>=80,"Green",IF(J49>=40,"Amber","Red")))))) | L49: Frontend Lead | M49: Engineering Manager | N49: 46143 | O49: 46204 | Q49: 46170 | R49: —
A50: FTR-050 | B50: Enterprise | C50: Billing overview | D50: Budget, invoices, rate cards UI | E50: P2 — High | F50: Phase 1 — MVP | G50: In Progress | H50: Complete | I50: Not Started | J50: =IF(G50="Completed",100,IF(G50="Deferred",0,IF(G50="Cancelled",0,IF(G50="Not Started",0,IF(G50="On Hold",IF(OR(H50="Complete",H50="N/A"),50,25),ROUND((IF(H50="Complete",100,IF(H50="In Progress",50,IF(H50="Blocked",25,0)))+IF(I50="Complete",100,IF(I50="In Progress",50,IF(I50="Blocked",25,IF(I50="N/A",100,0)))))/2,0)))))) | K50: =IF(G50="Completed","Green",IF(G50="Deferred","Grey",IF(G50="Cancelled","Grey",IF(G50="On Hold","Red",IF(J50>=80,"Green",IF(J50>=40,"Amber","Red")))))) | L50: Full Stack Developer | M50: Engineering Manager | N50: 46143 | O50: 46218 | Q50: 46170 | R50: FTR-012
A51: FTR-051 | B51: Enterprise | C51: Workforce roster | D51: Internal employee list and profile drawer | E51: P2 — High | F51: Phase 1 — MVP | G51: In Progress | H51: Complete | I51: Not Started | J51: =IF(G51="Completed",100,IF(G51="Deferred",0,IF(G51="Cancelled",0,IF(G51="Not Started",0,IF(G51="On Hold",IF(OR(H51="Complete",H51="N/A"),50,25),ROUND((IF(H51="Complete",100,IF(H51="In Progress",50,IF(H51="Blocked",25,0)))+IF(I51="Complete",100,IF(I51="In Progress",50,IF(I51="Blocked",25,IF(I51="N/A",100,0)))))/2,0)))))) | K51: =IF(G51="Completed","Green",IF(G51="Deferred","Grey",IF(G51="Cancelled","Grey",IF(G51="On Hold","Red",IF(J51>=80,"Green",IF(J51>=40,"Amber","Red")))))) | L51: Full Stack Developer | M51: Engineering Manager | N51: 46157 | O51: 46170 | Q51: 46170 | R51: FTR-094 | S51: Mock localStorage
A52: FTR-052 | B52: Enterprise | C52: Workforce CSV import | D52: Upload, preview, apply roster | E52: P2 — High | F52: Phase 1 — MVP | G52: In Progress | H52: Complete | I52: Not Started | J52: =IF(G52="Completed",100,IF(G52="Deferred",0,IF(G52="Cancelled",0,IF(G52="Not Started",0,IF(G52="On Hold",IF(OR(H52="Complete",H52="N/A"),50,25),ROUND((IF(H52="Complete",100,IF(H52="In Progress",50,IF(H52="Blocked",25,0)))+IF(I52="Complete",100,IF(I52="In Progress",50,IF(I52="Blocked",25,IF(I52="N/A",100,0)))))/2,0)))))) | K52: =IF(G52="Completed","Green",IF(G52="Deferred","Grey",IF(G52="Cancelled","Grey",IF(G52="On Hold","Red",IF(J52>=80,"Green",IF(J52>=40,"Amber","Red")))))) | L52: Full Stack Developer | M52: Engineering Manager | N52: 46157 | O52: 46203 | Q52: 46170 | R52: FTR-094
A53: FTR-053 | B53: Enterprise | C53: Manual add employee | D53: Form-based roster provisioning | E53: P2 — High | F53: Phase 1 — MVP | G53: In Progress | H53: Complete | I53: Not Started | J53: =IF(G53="Completed",100,IF(G53="Deferred",0,IF(G53="Cancelled",0,IF(G53="Not Started",0,IF(G53="On Hold",IF(OR(H53="Complete",H53="N/A"),50,25),ROUND((IF(H53="Complete",100,IF(H53="In Progress",50,IF(H53="Blocked",25,0)))+IF(I53="Complete",100,IF(I53="In Progress",50,IF(I53="Blocked",25,IF(I53="N/A",100,0)))))/2,0)))))) | K53: =IF(G53="Completed","Green",IF(G53="Deferred","Grey",IF(G53="Cancelled","Grey",IF(G53="On Hold","Red",IF(J53>=80,"Green",IF(J53>=40,"Amber","Red")))))) | L53: Full Stack Developer | M53: Engineering Manager | N53: 46157 | O53: 46170 | Q53: 46170 | R53: FTR-051
A54: FTR-054 | B54: Enterprise | C54: Settings — tenant & plan | D54: RBAC settings navigation and workspaces | E54: P2 — High | F54: Phase 1 — MVP | G54: In Progress | H54: Complete | I54: Not Started | J54: =IF(G54="Completed",100,IF(G54="Deferred",0,IF(G54="Cancelled",0,IF(G54="Not Started",0,IF(G54="On Hold",IF(OR(H54="Complete",H54="N/A"),50,25),ROUND((IF(H54="Complete",100,IF(H54="In Progress",50,IF(H54="Blocked",25,0)))+IF(I54="Complete",100,IF(I54="In Progress",50,IF(I54="Blocked",25,IF(I54="N/A",100,0)))))/2,0)))))) | K54: =IF(G54="Completed","Green",IF(G54="Deferred","Grey",IF(G54="Cancelled","Grey",IF(G54="On Hold","Red",IF(J54>=80,"Green",IF(J54>=40,"Amber","Red")))))) | L54: Full Stack Developer | M54: Engineering Manager | N54: 46143 | O54: 46188 | Q54: 46170 | R54: FTR-093
A55: FTR-055 | B55: Enterprise | C55: Profile & security settings | D55: Sessions, MFA display, security prefs | E55: P2 — High | F55: Phase 1 — MVP | G55: In Progress | H55: Complete | I55: In Progress | J55: =IF(G55="Completed",100,IF(G55="Deferred",0,IF(G55="Cancelled",0,IF(G55="Not Started",0,IF(G55="On Hold",IF(OR(H55="Complete",H55="N/A"),50,25),ROUND((IF(H55="Complete",100,IF(H55="In Progress",50,IF(H55="Blocked",25,0)))+IF(I55="Complete",100,IF(I55="In Progress",50,IF(I55="Blocked",25,IF(I55="N/A",100,0)))))/2,0)))))) | K55: =IF(G55="Completed","Green",IF(G55="Deferred","Grey",IF(G55="Cancelled","Grey",IF(G55="On Hold","Red",IF(J55>=80,"Green",IF(J55>=40,"Amber","Red")))))) | L55: Full Stack Developer | M55: Engineering Manager | N55: 46143 | O55: 46188 | Q55: 46170 | R55: FTR-004
A56: FTR-056 | B56: Enterprise | C56: Notifications centre | D56: In-app notification feed | E56: P3 — Medium | F56: Phase 1 — MVP | G56: In Progress | H56: Complete | I56: Not Started | J56: =IF(G56="Completed",100,IF(G56="Deferred",0,IF(G56="Cancelled",0,IF(G56="Not Started",0,IF(G56="On Hold",IF(OR(H56="Complete",H56="N/A"),50,25),ROUND((IF(H56="Complete",100,IF(H56="In Progress",50,IF(H56="Blocked",25,0)))+IF(I56="Complete",100,IF(I56="In Progress",50,IF(I56="Blocked",25,IF(I56="N/A",100,0)))))/2,0)))))) | K56: =IF(G56="Completed","Green",IF(G56="Deferred","Grey",IF(G56="Cancelled","Grey",IF(G56="On Hold","Red",IF(J56>=80,"Green",IF(J56>=40,"Amber","Red")))))) | L56: Frontend Lead | M56: Engineering Manager | N56: 46157 | O56: 46204 | Q56: 46170 | R56: FTR-093
A57: FTR-057 | B57: Enterprise | C57: Enterprise onboarding | D57: First-time admin onboarding flow | E57: P2 — High | F57: Phase 1 — MVP | G57: In Progress | H57: Complete | I57: In Progress | J57: =IF(G57="Completed",100,IF(G57="Deferred",0,IF(G57="Cancelled",0,IF(G57="Not Started",0,IF(G57="On Hold",IF(OR(H57="Complete",H57="N/A"),50,25),ROUND((IF(H57="Complete",100,IF(H57="In Progress",50,IF(H57="Blocked",25,0)))+IF(I57="Complete",100,IF(I57="In Progress",50,IF(I57="Blocked",25,IF(I57="N/A",100,0)))))/2,0)))))) | K57: =IF(G57="Completed","Green",IF(G57="Deferred","Grey",IF(G57="Cancelled","Grey",IF(G57="On Hold","Red",IF(J57>=80,"Green",IF(J57>=40,"Amber","Red")))))) | L57: Full Stack Developer | M57: Engineering Manager | N57: 46127 | O57: 46174 | Q57: 46170 | R57: —
A58: FTR-058 | B58: Enterprise | C58: Analytics console | D58: Economic and governance analytics | E58: P4 — Low | F58: Phase 2 | G58: Deferred | H58: Complete | I58: Not Started | J58: =IF(G58="Completed",100,IF(G58="Deferred",0,IF(G58="Cancelled",0,IF(G58="Not Started",0,IF(G58="On Hold",IF(OR(H58="Complete",H58="N/A"),50,25),ROUND((IF(H58="Complete",100,IF(H58="In Progress",50,IF(H58="Blocked",25,0)))+IF(I58="Complete",100,IF(I58="In Progress",50,IF(I58="Blocked",25,IF(I58="N/A",100,0)))))/2,0)))))) | K58: =IF(G58="Completed","Green",IF(G58="Deferred","Grey",IF(G58="Cancelled","Grey",IF(G58="On Hold","Red",IF(J58>=80,"Green",IF(J58>=40,"Amber","Red")))))) | L58: Unassigned | M58: Engineering Manager | O58: 46266 | Q58: 46170 | R58: — | S58: Phase 2 scope
A59: FTR-059 | B59: Enterprise | C59: Compliance module | D59: ESG, evidence locker, PODL | E59: P4 — Low | F59: Phase 2 | G59: Deferred | H59: Complete | I59: Not Started | J59: =IF(G59="Completed",100,IF(G59="Deferred",0,IF(G59="Cancelled",0,IF(G59="Not Started",0,IF(G59="On Hold",IF(OR(H59="Complete",H59="N/A"),50,25),ROUND((IF(H59="Complete",100,IF(H59="In Progress",50,IF(H59="Blocked",25,0)))+IF(I59="Complete",100,IF(I59="In Progress",50,IF(I59="Blocked",25,IF(I59="N/A",100,0)))))/2,0)))))) | K59: =IF(G59="Completed","Green",IF(G59="Deferred","Grey",IF(G59="Cancelled","Grey",IF(G59="On Hold","Red",IF(J59>=80,"Green",IF(J59>=40,"Amber","Red")))))) | L59: Unassigned | M59: Engineering Manager | O59: 46266 | Q59: 46170 | R59: — | S59: Phase 2 scope
A60: FTR-060 | B60: Enterprise | C60: Audit log export | D60: Enterprise audit trail export | E60: P4 — Low | F60: Phase 2 | G60: Deferred | H60: In Progress | I60: In Progress | J60: =IF(G60="Completed",100,IF(G60="Deferred",0,IF(G60="Cancelled",0,IF(G60="Not Started",0,IF(G60="On Hold",IF(OR(H60="Complete",H60="N/A"),50,25),ROUND((IF(H60="Complete",100,IF(H60="In Progress",50,IF(H60="Blocked",25,0)))+IF(I60="Complete",100,IF(I60="In Progress",50,IF(I60="Blocked",25,IF(I60="N/A",100,0)))))/2,0)))))) | K60: =IF(G60="Completed","Green",IF(G60="Deferred","Grey",IF(G60="Cancelled","Grey",IF(G60="On Hold","Red",IF(J60>=80,"Green",IF(J60>=40,"Amber","Red")))))) | L60: Backend Lead | M60: Engineering Manager | N60: 46204 | O60: 46235 | Q60: 46170 | R60: FTR-015
A61: FTR-070 | B61: Mentor | C61: Dashboard | D61: Mentor home with queue summary | E61: P1 — Critical | F61: Phase 1 — MVP | G61: In Progress | H61: Complete | I61: Not Started | J61: =IF(G61="Completed",100,IF(G61="Deferred",0,IF(G61="Cancelled",0,IF(G61="Not Started",0,IF(G61="On Hold",IF(OR(H61="Complete",H61="N/A"),50,25),ROUND((IF(H61="Complete",100,IF(H61="In Progress",50,IF(H61="Blocked",25,0)))+IF(I61="Complete",100,IF(I61="In Progress",50,IF(I61="Blocked",25,IF(I61="N/A",100,0)))))/2,0)))))) | K61: =IF(G61="Completed","Green",IF(G61="Deferred","Grey",IF(G61="Cancelled","Grey",IF(G61="On Hold","Red",IF(J61>=80,"Green",IF(J61>=40,"Amber","Red")))))) | L61: Frontend Lead | M61: Engineering Manager | N61: 46113 | O61: 46143 | Q61: 46170 | R61: —
A62: FTR-071 | B62: Mentor | C62: Review queue | D62: Pending submissions awaiting review | E62: P1 — Critical | F62: Phase 1 — MVP | G62: In Progress | H62: Complete | I62: Not Started | J62: =IF(G62="Completed",100,IF(G62="Deferred",0,IF(G62="Cancelled",0,IF(G62="Not Started",0,IF(G62="On Hold",IF(OR(H62="Complete",H62="N/A"),50,25),ROUND((IF(H62="Complete",100,IF(H62="In Progress",50,IF(H62="Blocked",25,0)))+IF(I62="Complete",100,IF(I62="In Progress",50,IF(I62="Blocked",25,IF(I62="N/A",100,0)))))/2,0)))))) | K62: =IF(G62="Completed","Green",IF(G62="Deferred","Grey",IF(G62="Cancelled","Grey",IF(G62="On Hold","Red",IF(J62>=80,"Green",IF(J62>=40,"Amber","Red")))))) | L62: Full Stack Developer | M62: Engineering Manager | N62: 46127 | O62: 46203 | Q62: 46170 | R62: FTR-092
A63: FTR-072 | B63: Mentor | C63: Active review detail | D63: Rubric scoring and approve / rework | E63: P1 — Critical | F63: Phase 1 — MVP | G63: In Progress | H63: Complete | I63: Not Started | J63: =IF(G63="Completed",100,IF(G63="Deferred",0,IF(G63="Cancelled",0,IF(G63="Not Started",0,IF(G63="On Hold",IF(OR(H63="Complete",H63="N/A"),50,25),ROUND((IF(H63="Complete",100,IF(H63="In Progress",50,IF(H63="Blocked",25,0)))+IF(I63="Complete",100,IF(I63="In Progress",50,IF(I63="Blocked",25,IF(I63="N/A",100,0)))))/2,0)))))) | K63: =IF(G63="Completed","Green",IF(G63="Deferred","Grey",IF(G63="Cancelled","Grey",IF(G63="On Hold","Red",IF(J63>=80,"Green",IF(J63>=40,"Amber","Red")))))) | L63: Full Stack Developer | M63: Engineering Manager | N63: 46127 | O63: 46203 | Q63: 46170 | R63: FTR-092
A64: FTR-073 | B64: Mentor | C64: Escalation management | D64: Escalated review resolution | E64: P2 — High | F64: Phase 1 — MVP | G64: In Progress | H64: Complete | I64: Not Started | J64: =IF(G64="Completed",100,IF(G64="Deferred",0,IF(G64="Cancelled",0,IF(G64="Not Started",0,IF(G64="On Hold",IF(OR(H64="Complete",H64="N/A"),50,25),ROUND((IF(H64="Complete",100,IF(H64="In Progress",50,IF(H64="Blocked",25,0)))+IF(I64="Complete",100,IF(I64="In Progress",50,IF(I64="Blocked",25,IF(I64="N/A",100,0)))))/2,0)))))) | K64: =IF(G64="Completed","Green",IF(G64="Deferred","Grey",IF(G64="Cancelled","Grey",IF(G64="On Hold","Red",IF(J64>=80,"Green",IF(J64>=40,"Amber","Red")))))) | L64: Frontend Lead | M64: Engineering Manager | N64: 46143 | O64: 46204 | Q64: 46170 | R64: —
A65: FTR-074 | B65: Mentor | C65: Mentorship sessions | D65: Session notes and history | E65: P2 — High | F65: Phase 1 — MVP | G65: In Progress | H65: Complete | I65: Not Started | J65: =IF(G65="Completed",100,IF(G65="Deferred",0,IF(G65="Cancelled",0,IF(G65="Not Started",0,IF(G65="On Hold",IF(OR(H65="Complete",H65="N/A"),50,25),ROUND((IF(H65="Complete",100,IF(H65="In Progress",50,IF(H65="Blocked",25,0)))+IF(I65="Complete",100,IF(I65="In Progress",50,IF(I65="Blocked",25,IF(I65="N/A",100,0)))))/2,0)))))) | K65: =IF(G65="Completed","Green",IF(G65="Deferred","Grey",IF(G65="Cancelled","Grey",IF(G65="On Hold","Red",IF(J65>=80,"Green",IF(J65>=40,"Amber","Red")))))) | L65: Frontend Lead | M65: Engineering Manager | N65: 46157 | O65: 46218 | Q65: 46170 | R65: —
A66: FTR-075 | B66: Mentor | C66: Review history | D66: Completed reviews archive | E66: P2 — High | F66: Phase 1 — MVP | G66: In Progress | H66: Complete | I66: Not Started | J66: =IF(G66="Completed",100,IF(G66="Deferred",0,IF(G66="Cancelled",0,IF(G66="Not Started",0,IF(G66="On Hold",IF(OR(H66="Complete",H66="N/A"),50,25),ROUND((IF(H66="Complete",100,IF(H66="In Progress",50,IF(H66="Blocked",25,0)))+IF(I66="Complete",100,IF(I66="In Progress",50,IF(I66="Blocked",25,IF(I66="N/A",100,0)))))/2,0)))))) | K66: =IF(G66="Completed","Green",IF(G66="Deferred","Grey",IF(G66="Cancelled","Grey",IF(G66="On Hold","Red",IF(J66>=80,"Green",IF(J66>=40,"Amber","Red")))))) | L66: Frontend Lead | M66: Engineering Manager | N66: 46143 | O66: 46174 | Q66: 46170 | R66: —
A67: FTR-076 | B67: Mentor | C67: Profile & settings | D67: Mentor preferences | E67: P3 — Medium | F67: Phase 1 — MVP | G67: In Progress | H67: Complete | I67: Not Started | J67: =IF(G67="Completed",100,IF(G67="Deferred",0,IF(G67="Cancelled",0,IF(G67="Not Started",0,IF(G67="On Hold",IF(OR(H67="Complete",H67="N/A"),50,25),ROUND((IF(H67="Complete",100,IF(H67="In Progress",50,IF(H67="Blocked",25,0)))+IF(I67="Complete",100,IF(I67="In Progress",50,IF(I67="Blocked",25,IF(I67="N/A",100,0)))))/2,0)))))) | K67: =IF(G67="Completed","Green",IF(G67="Deferred","Grey",IF(G67="Cancelled","Grey",IF(G67="On Hold","Red",IF(J67>=80,"Green",IF(J67>=40,"Amber","Red")))))) | L67: Frontend Lead | M67: Engineering Manager | N67: 46157 | O67: 46204 | Q67: 46170 | R67: —
A68: FTR-080 | B68: Admin | C68: Dashboard | D68: Platform operations overview | E68: P2 — High | F68: Phase 1 — MVP | G68: In Progress | H68: Complete | I68: Not Started | J68: =IF(G68="Completed",100,IF(G68="Deferred",0,IF(G68="Cancelled",0,IF(G68="Not Started",0,IF(G68="On Hold",IF(OR(H68="Complete",H68="N/A"),50,25),ROUND((IF(H68="Complete",100,IF(H68="In Progress",50,IF(H68="Blocked",25,0)))+IF(I68="Complete",100,IF(I68="In Progress",50,IF(I68="Blocked",25,IF(I68="N/A",100,0)))))/2,0)))))) | K68: =IF(G68="Completed","Green",IF(G68="Deferred","Grey",IF(G68="Cancelled","Grey",IF(G68="On Hold","Red",IF(J68>=80,"Green",IF(J68>=40,"Amber","Red")))))) | L68: Frontend Lead | M68: Engineering Manager | N68: 46113 | O68: 46174 | Q68: 46170 | R68: —
A69: FTR-081 | B69: Admin | C69: Tenant provisioning wizard | D69: Create tenant, tier, invite admin | E69: P2 — High | F69: Phase 1 — MVP | G69: In Progress | H69: Complete | I69: Not Started | J69: =IF(G69="Completed",100,IF(G69="Deferred",0,IF(G69="Cancelled",0,IF(G69="Not Started",0,IF(G69="On Hold",IF(OR(H69="Complete",H69="N/A"),50,25),ROUND((IF(H69="Complete",100,IF(H69="In Progress",50,IF(H69="Blocked",25,0)))+IF(I69="Complete",100,IF(I69="In Progress",50,IF(I69="Blocked",25,IF(I69="N/A",100,0)))))/2,0)))))) | K69: =IF(G69="Completed","Green",IF(G69="Deferred","Grey",IF(G69="Cancelled","Grey",IF(G69="On Hold","Red",IF(J69>=80,"Green",IF(J69>=40,"Amber","Red")))))) | L69: Full Stack Developer | M69: Engineering Manager | N69: 46143 | O69: 46204 | Q69: 46170 | R69: FTR-008
A70: FTR-082 | B70: Admin | C70: Tenant subscription management | D70: Plan, usage, change history | E70: P2 — High | F70: Phase 1 — MVP | G70: In Progress | H70: Complete | I70: In Progress | J70: =IF(G70="Completed",100,IF(G70="Deferred",0,IF(G70="Cancelled",0,IF(G70="Not Started",0,IF(G70="On Hold",IF(OR(H70="Complete",H70="N/A"),50,25),ROUND((IF(H70="Complete",100,IF(H70="In Progress",50,IF(H70="Blocked",25,0)))+IF(I70="Complete",100,IF(I70="In Progress",50,IF(I70="Blocked",25,IF(I70="N/A",100,0)))))/2,0)))))) | K70: =IF(G70="Completed","Green",IF(G70="Deferred","Grey",IF(G70="Cancelled","Grey",IF(G70="On Hold","Red",IF(J70>=80,"Green",IF(J70>=40,"Amber","Red")))))) | L70: Full Stack Developer | M70: Engineering Manager | N70: 46143 | O70: 46188 | Q70: 46170 | R70: FTR-016
A71: FTR-083 | B71: Admin | C71: User management | D71: Roles, invitations, directory | E71: P2 — High | F71: Phase 1 — MVP | G71: In Progress | H71: Complete | I71: Not Started | J71: =IF(G71="Completed",100,IF(G71="Deferred",0,IF(G71="Cancelled",0,IF(G71="Not Started",0,IF(G71="On Hold",IF(OR(H71="Complete",H71="N/A"),50,25),ROUND((IF(H71="Complete",100,IF(H71="In Progress",50,IF(H71="Blocked",25,0)))+IF(I71="Complete",100,IF(I71="In Progress",50,IF(I71="Blocked",25,IF(I71="N/A",100,0)))))/2,0)))))) | K71: =IF(G71="Completed","Green",IF(G71="Deferred","Grey",IF(G71="Cancelled","Grey",IF(G71="On Hold","Red",IF(J71>=80,"Green",IF(J71>=40,"Amber","Red")))))) | L71: Full Stack Developer | M71: Engineering Manager | N71: 46143 | O71: 46204 | Q71: 46170 | R71: FTR-007
... A75: FTR-087 | B75: Admin | C75: KYC review queue | D75: Contributor onboarding case review | E75: P2 — High | F75: Phase 1 — MVP | G75: In Progress | H75: Complete | I75: Not Started | J75: =IF(G75="Completed",100,IF(G75="Deferred",0,IF(G75="Cancelled",0,IF(G75="Not Started",0,IF(G75="On Hold",IF(OR(H75="Complete",H75="N/A"),50,25),ROUND((IF(H75="Complete",100,IF(H75="In Progress",50,IF(H75="Blocked",25,0)))+IF(I75="Complete",100,IF(I75="In Progress",50,IF(I75="Blocked",25,IF(I75="N/A",100,0)))))/2,0)))))) | K75: =IF(G75="Completed","Green",IF(G75="Deferred","Grey",IF(G75="Cancelled","Grey",IF(G75="On Hold","Red",IF(J75>=80,"Green",IF(J75>=40,"Amber","Red")))))) | L75: Full Stack Developer | M75: Engineering Manager | N75: 46157 | O75: 46204 | Q75: 46170 | R75: FTR-024
A76: FTR-088 | B76: Admin | C76: Governance & safety reports | D76: Platform-wide triage | E76: P4 — Low | F76: Phase 2 | G76: Deferred | H76: In Progress | I76: Not Started | J76: =IF(G76="Completed",100,IF(G76="Deferred",0,IF(G76="Cancelled",0,IF(G76="Not Started",0,IF(G76="On Hold",IF(OR(H76="Complete",H76="N/A"),50,25),ROUND((IF(H76="Complete",100,IF(H76="In Progress",50,IF(H76="Blocked",25,0)))+IF(I76="Complete",100,IF(I76="In Progress",50,IF(I76="Blocked",25,IF(I76="N/A",100,0)))))/2,0)))))) | K76: =IF(G76="Completed","Green",IF(G76="Deferred","Grey",IF(G76="Cancelled","Grey",IF(G76="On Hold","Red",IF(J76>=80,"Green",IF(J76>=40,"Amber","Red")))))) | L76: Unassigned | M76: Engineering Manager | O76: 46266 | Q76: 46170 | R76: —
A77: FTR-090 | B77: Backend | C77: Task persistence (Postgres) | D77: Migrate task store from localStorage | E77: P1 — Critical | F77: Phase 1 — Hardening | G77: Not Started | H77: N/A | I77: Not Started | J77: =IF(G77="Completed",100,IF(G77="Deferred",0,IF(G77="Cancelled",0,IF(G77="Not Started",0,IF(G77="On Hold",IF(OR(H77="Complete",H77="N/A"),50,25),ROUND((IF(H77="Complete",100,IF(H77="In Progress",50,IF(H77="Blocked",25,0)))+IF(I77="Complete",100,IF(I77="In Progress",50,IF(I77="Blocked",25,IF(I77="N/A",100,0)))))/2,0)))))) | K77: =IF(G77="Completed","Green",IF(G77="Deferred","Grey",IF(G77="Cancelled","Grey",IF(G77="On Hold","Red",IF(J77>=80,"Green",IF(J77>=40,"Amber","Red")))))) | L77: Backend Lead | M77: Engineering Manager | N77: 46174 | O77: 46218 | Q77: 46170 | R77: FTR-008 | S77: Slice 5 — prod blocker
A78: FTR-091 | B78: Backend | C78: SOW / project / decomposition APIs | D78: Prisma models and CRUD endpoints | E78: P1 — Critical | F78: Phase 1 — Hardening | G78: In Progress | H78: N/A | I78: In Progress | J78: =IF(G78="Completed",100,IF(G78="Deferred",0,IF(G78="Cancelled",0,IF(G78="Not Started",0,IF(G78="On Hold",IF(OR(H78="Complete",H78="N/A"),50,25),ROUND((IF(H78="Complete",100,IF(H78="In Progress",50,IF(H78="Blocked",25,0)))+IF(I78="Complete",100,IF(I78="In Progress",50,IF(I78="Blocked",25,IF(I78="N/A",100,0)))))/2,0)))))) | K78: =IF(G78="Completed","Green",IF(G78="Deferred","Grey",IF(G78="Cancelled","Grey",IF(G78="On Hold","Red",IF(J78>=80,"Green",IF(J78>=40,"Amber","Red")))))) | L78: Backend Lead | M78: Engineering Manager | N78: 46157 | O78: 46233 | Q78: 46170 | R78: FTR-008
A79: FTR-092 | B79: Backend | C79: Mentor decision persistence | D79: Persist approve / rework to database | E79: P1 — Critical | F79: Phase 1 — Hardening | G79: Not Started | H79: N/A | I79: Not Started | J79: =IF(G79="Completed",100,IF(G79="Deferred",0,IF(G79="Cancelled",0,IF(G79="Not Started",0,IF(G79="On Hold",IF(OR(H79="Complete",H79="N/A"),50,25),ROUND((IF(H79="Complete",100,IF(H79="In Progress",50,IF(H79="Blocked",25,0)))+IF(I79="Complete",100,IF(I79="In Progress",50,IF(I79="Blocked",25,IF(I79="N/A",100,0)))))/2,0)))))) | K79: =IF(G79="Completed","Green",IF(G79="Deferred","Grey",IF(G79="Cancelled","Grey",IF(G79="On Hold","Red",IF(J79>=80,"Green",IF(J79>=40,"Amber","Red")))))) | L79: Backend Lead | M79: Engineering Manager | N79: 46174 | O79: 46218 | Q79: 46170 | R79: FTR-090
A80: FTR-093 | B80: Backend | C80: Settings & preferences API | D80: OperatorPreferences model + endpoints | E80: P2 — High | F80: Phase 1 — Hardening | G80: Not Started | H80: N/A | I80: Not Started | J80: =IF(G80="Completed",100,IF(G80="Deferred",0,IF(G80="Cancelled",0,IF(G80="Not Started",0,IF(G80="On Hold",IF(OR(H80="Complete",H80="N/A"),50,25),ROUND((IF(H80="Complete",100,IF(H80="In Progress",50,IF(H80="Blocked",25,0)))+IF(I80="Complete",100,IF(I80="In Progress",50,IF(I80="Blocked",25,IF(I80="N/A",100,0)))))/2,0)))))) | K80: =IF(G80="Completed","Green",IF(G80="Deferred","Grey",IF(G80="Cancelled","Grey",IF(G80="On Hold","Red",IF(J80>=80,"Green",IF(J80>=40,"Amber","Red")))))) | L80: Backend Lead | M80: Engineering Manager | N80: 46188 | O80: 46204 | Q80: 46170 | R80: FTR-008
A81: FTR-094 | B81: Backend | C81: Workforce API (production) | D81: Wire workforce routes to Prisma | E81: P2 — High | F81: Phase 1 — Hardening | G81: In Progress | H81: N/A | I81: In Progress | J81: =IF(G81="Completed",100,IF(G81="Deferred",0,IF(G81="Cancelled",0,IF(G81="Not Started",0,IF(G81="On Hold",IF(OR(H81="Complete",H81="N/A"),50,25),ROUND((IF(H81="Complete",100,IF(H81="In Progress",50,IF(H81="Blocked",25,0)))+IF(I81="Complete",100,IF(I81="In Progress",50,IF(I81="Blocked",25,IF(I81="N/A",100,0)))))/2,0)))))) | K81: =IF(G81="Completed","Green",IF(G81="Deferred","Grey",IF(G81="Cancelled","Grey",IF(G81="On Hold","Red",IF(J81>=80,"Green",IF(J81>=40,"Amber","Red")))))) | L81: Backend Lead | M81: Engineering Manager | N81: 46157 | O81: 46204 | Q81: 46170 | R81: FTR-051
A82: FTR-095 | B82: Backend | C82: Enterprise SSO / HRIS | D82: SAML, OIDC; CSV import path | E82: P2 — High | F82: Phase 1 — Hardening | G82: Not Started | H82: In Progress | I82: Not Started | J82: =IF(G82="Completed",100,IF(G82="Deferred",0,IF(G82="Cancelled",0,IF(G82="Not Started",0,IF(G82="On Hold",IF(OR(H82="Complete",H82="N/A"),50,25),ROUND((IF(H82="Complete",100,IF(H82="In Progress",50,IF(H82="Blocked",25,0)))+IF(I82="Complete",100,IF(I82="In Progress",50,IF(I82="Blocked",25,IF(I82="N/A",100,0)))))/2,0)))))) | K82: =IF(G82="Completed","Green",IF(G82="Deferred","Grey",IF(G82="Cancelled","Grey",IF(G82="On Hold","Red",IF(J82>=80,"Green",IF(J82>=40,"Amber","Red")))))) | L82: Integrations Lead | M82: Engineering Manager | N82: 46174 | O82: 46235 | Q82: 46170 | R82: FTR-003
A83: FTR-096 | B83: Backend | C83: Outbound webhooks | D83: Jira, Slack, generic connectors | E83: P3 — Medium | F83: Phase 2 | G83: Not Started | H83: N/A | I83: Not Started | J83: =IF(G83="Completed",100,IF(G83="Deferred",0,IF(G83="Cancelled",0,IF(G83="Not Started",0,IF(G83="On Hold",IF(OR(H83="Complete",H83="N/A"),50,25),ROUND((IF(H83="Complete",100,IF(H83="In Progress",50,IF(H83="Blocked",25,0)))+IF(I83="Complete",100,IF(I83="In Progress",50,IF(I83="Blocked",25,IF(I83="N/A",100,0)))))/2,0)))))) | K83: =IF(G83="Completed","Green",IF(G83="Deferred","Grey",IF(G83="Cancelled","Grey",IF(G83="On Hold","Red",IF(J83>=80,"Green",IF(J83>=40,"Amber","Red")))))) | L83: Integrations Lead | M83: Engineering Manager | N83: 46204 | O83: 46249 | Q83: 46170 | R83: —
A84: FTR-097 | B84: Backend | C84: Assistive AI agents | D84: SOW intake, decomposition, review AI | E84: P2 — High | F84: Phase 1 — Hardening | G84: In Progress | H84: In Progress | I84: In Progress | J84: =IF(G84="Completed",100,IF(G84="Deferred",0,IF(G84="Cancelled",0,IF(G84="Not Started",0,IF(G84="On Hold",IF(OR(H84="Complete",H84="N/A"),50,25),ROUND((IF(H84="Complete",100,IF(H84="In Progress",50,IF(H84="Blocked",25,0)))+IF(I84="Complete",100,IF(I84="In Progress",50,IF(I84="Blocked",25,IF(I84="N/A",100,0)))))/2,0)))))) | K84: =IF(G84="Completed","Green",IF(G84="Deferred","Grey",IF(G84="Cancelled","Grey",IF(G84="On Hold","Red",IF(J84>=80,"Green",IF(J84>=40,"Amber","Red")))))) | L84: AI / ML Engineer | M84: Engineering Manager | N84: 46143 | O84: 46235 | Q84: 46170 | R84: —
A85: FTR-098 | B85: Backend | C85: Server-side exports | D85: PDF / CSV report generation | E85: P3 — Medium | F85: Phase 2 | G85: Not Started | H85: N/A | I85: Not Started | J85: =IF(G85="Completed",100,IF(G85="Deferred",0,IF(G85="Cancelled",0,IF(G85="Not Started",0,IF(G85="On Hold",IF(OR(H85="Complete",H85="N/A"),50,25),ROUND((IF(H85="Complete",100,IF(H85="In Progress",50,IF(H85="Blocked",25,0)))+IF(I85="Complete",100,IF(I85="In Progress",50,IF(I85="Blocked",25,IF(I85="N/A",100,0)))))/2,0)))))) | K85: =IF(G85="Completed","Green",IF(G85="Deferred","Grey",IF(G85="Cancelled","Grey",IF(G85="On Hold","Red",IF(J85>=80,"Green",IF(J85>=40,"Amber","Red")))))) | L85: Backend Lead | M85: Engineering Manager | N85: 46204 | O85: 46235 | Q85: 46170 | R85: —
A86: FTR-099 | B86: Backend | C86: Real-time updates (SSE / WS) | D86: Live activity without refresh | E86: P3 — Medium | F86: Phase 2 | G86: Not Started | H86: N/A | I86: Not Started | J86: =IF(G86="Completed",100,IF(G86="Deferred",0,IF(G86="Cancelled",0,IF(G86="Not Started",0,IF(G86="On Hold",IF(OR(H86="Complete",H86="N/A"),50,25),ROUND((IF(H86="Complete",100,IF(H86="In Progress",50,IF(H86="Blocked",25,0)))+IF(I86="Complete",100,IF(I86="In Progress",50,IF(I86="Blocked",25,IF(I86="N/A",100,0)))))/2,0)))))) | K86: =IF(G86="Completed","Green",IF(G86="Deferred","Grey",IF(G86="Cancelled","Grey",IF(G86="On Hold","Red",IF(J86>=80,"Green",IF(J86>=40,"Amber","Red")))))) | L86: DevOps / SRE | M86: Engineering Manager | N86: 46235 | O86: 46266 | Q86: 46170 | R86: —
A87: FTR-100 | B87: Backend | C87: WCAG 2.1 AA audit | D87: Accessibility compliance gate | E87: P2 — High | F87: Phase 1 — Hardening | G87: Not Started | H87: In Progress | I87: Not Started | J87: =IF(G87="Completed",100,IF(G87="Deferred",0,IF(G87="Cancelled",0,IF(G87="Not Started",0,IF(G87="On Hold",IF(OR(H87="Complete",H87="N/A"),50,25),ROUND((IF(H87="Complete",100,IF(H87="In Progress",50,IF(H87="Blocked",25,0)))+IF(I87="Complete",100,IF(I87="In Progress",50,IF(I87="Blocked",25,IF(I87="N/A",100,0)))))/2,0)))))) | K87: =IF(G87="Completed","Green",IF(G87="Deferred","Grey",IF(G87="Cancelled","Grey",IF(G87="On Hold","Red",IF(J87>=80,"Green",IF(J87>=40,"Amber","Red")))))) | L87: QA Lead | M87: Engineering Manager | N87: 46204 | O87: 46264 | Q87: 46170 | R87: — | S87: Phase 1D gate

Sheet Dashboard
A1: Program Dashboard
A2: As of 28 May 2026 · sourced from Feature Register
A4: Total features | C4: Completed | E4: In progress | G4: Not started
A5: =COUNTA('Feature Register'!A12:A87) | C5: =COUNTIF('Feature Register'!G12:G87,"Completed") | E5: =COUNTIF('Feature Register'!G12:G87,"In Progress") | G5: =COUNTIF('Feature Register'!G12:G87,"Not Started")
A7: P1 critical (open) | C7: Avg % complete | E7: Red / Amber (RAG) | G7: Deferred (Phase 2)
A8: =COUNTIFS('Feature Register'!E12:E87,"P1*",'Feature Register'!G12:G87,"<>Completed",'Feature Register'!G12:G87,"<>Deferred",'Feature Register'!G12:G87,"<>Cancelled") | C8: =IFERROR(AVERAGE('Feature Register'!J12:J87),0) | E8: =COUNTIF('Feature Register'!K12:K87,"Red")&" / "&COUNTIF('Feature Register'!K12:K87,"Amber") | G8: =COUNTIF('Feature Register'!G12:G87,"Deferred")
A12: By module
A13: Module | B13: Total | C13: Completed | D13: In Progress | E13: Not Started | F13: Avg %
A14: Platform | B14: =COUNTIF('Feature Register'!B12:B87,"Platform") | C14: =COUNTIFS('Feature Register'!B12:B87,"Platform",'Feature Register'!G12:G87,"Completed") | D14: =COUNTIFS('Feature Register'!B12:B87,"Platform",'Feature Register'!G12:G87,"In Progress") | E14: =COUNTIFS('Feature Register'!B12:B87,"Platform",'Feature Register'!G12:G87,"Not Started") | F14: =IFERROR(AVERAGEIF('Feature Register'!B12:B87,"Platform",'Feature Register'!J12:J87),0)
A15: Contributor | B15: =COUNTIF('Feature Register'!B12:B87,"Contributor") | C15: =COUNTIFS('Feature Register'!B12:B87,"Contributor",'Feature Register'!G12:G87,"Completed") | D15: =COUNTIFS('Feature Register'!B12:B87,"Contributor",'Feature Register'!G12:G87,"In Progress") | E15: =COUNTIFS('Feature Register'!B12:B87,"Contributor",'Feature Register'!G12:G87,"Not Started") | F15: =IFERROR(AVERAGEIF('Feature Register'!B12:B87,"Contributor",'Feature Register'!J12:J87),0)
A16: Enterprise | B16: =COUNTIF('Feature Register'!B12:B87,"Enterprise") | C16: =COUNTIFS('Feature Register'!B12:B87,"Enterprise",'Feature Register'!G12:G87,"Completed") | D16: =COUNTIFS('Feature Register'!B12:B87,"Enterprise",'Feature Register'!G12:G87,"In Progress") | E16: =COUNTIFS('Feature Register'!B12:B87,"Enterprise",'Feature Register'!G12:G87,"Not Started") | F16: =IFERROR(AVERAGEIF('Feature Register'!B12:B87,"Enterprise",'Feature Register'!J12:J87),0)
A17: Mentor | B17: =COUNTIF('Feature Register'!B12:B87,"Mentor") | C17: =COUNTIFS('Feature Register'!B12:B87,"Mentor",'Feature Register'!G12:G87,"Completed") | D17: =COUNTIFS('Feature Register'!B12:B87,"Mentor",'Feature Register'!G12:G87,"In Progress") | E17: =COUNTIFS('Feature Register'!B12:B87,"Mentor",'Feature Register'!G12:G87,"Not Started") | F17: =IFERROR(AVERAGEIF('Feature Register'!B12:B87,"Mentor",'Feature Register'!J12:J87),0)
A18: Admin | B18: =COUNTIF('Feature Register'!B12:B87,"Admin") | C18: =COUNTIFS('Feature Register'!B12:B87,"Admin",'Feature Register'!G12:G87,"Completed") | D18: =COUNTIFS('Feature Register'!B12:B87,"Admin",'Feature Register'!G12:G87,"In Progress") | E18: =COUNTIFS('Feature Register'!B12:B87,"Admin",'Feature Register'!G12:G87,"Not Started") | F18: =IFERROR(AVERAGEIF('Feature Register'!B12:B87,"Admin",'Feature Register'!J12:J87),0)
A19: Backend | B19: =COUNTIF('Feature Register'!B12:B87,"Backend") | C19: =COUNTIFS('Feature Register'!B12:B87,"Backend",'Feature Register'!G12:G87,"Completed") | D19: =COUNTIFS('Feature Register'!B12:B87,"Backend",'Feature Register'!G12:G87,"In Progress") | E19: =COUNTIFS('Feature Register'!B12:B87,"Backend",'Feature Register'!G12:G87,"Not Started") | F19: =IFERROR(AVERAGEIF('Feature Register'!B12:B87,"Backend",'Feature Register'!J12:J87),0)

Sheet Resource Plan
A1: Resource Plan — by assignee
A2: Standard workload view · who owns how many open items
A4: Assigned To | B4: Total assigned | C4: Completed | D4: In progress | E4: Not started | F4: Open P1 items
A5: Product Manager | B5: =COUNTIF('Feature Register'!L12:L87,A5) | C5: =COUNTIFS('Feature Register'!L12:L87,A5,'Feature Register'!G12:G87,"Completed") | D5: =COUNTIFS('Feature Register'!L12:L87,A5,'Feature Register'!G12:G87,"In Progress") | E5: =COUNTIFS('Feature Register'!L12:L87,A5,'Feature Register'!G12:G87,"Not Started") | F5: =COUNTIFS('Feature Register'!L12:L87,A5,'Feature Register'!E12:E87,"P1*",'Feature Register'!G12:G87,"<>Completed")
A6: Engineering Manager | B6: =COUNTIF('Feature Register'!L12:L87,A6) | C6: =COUNTIFS('Feature Register'!L12:L87,A6,'Feature Register'!G12:G87,"Completed") | D6: =COUNTIFS('Feature Register'!L12:L87,A6,'Feature Register'!G12:G87,"In Progress") | E6: =COUNTIFS('Feature Register'!L12:L87,A6,'Feature Register'!G12:G87,"Not Started") | F6: =COUNTIFS('Feature Register'!L12:L87,A6,'Feature Register'!E12:E87,"P1*",'Feature Register'!G12:G87,"<>Completed")
A7: Frontend Lead | B7: =COUNTIF('Feature Register'!L12:L87,A7) | C7: =COUNTIFS('Feature Register'!L12:L87,A7,'Feature Register'!G12:G87,"Completed") | D7: =COUNTIFS('Feature Register'!L12:L87,A7,'Feature Register'!G12:G87,"In Progress") | E7: =COUNTIFS('Feature Register'!L12:L87,A7,'Feature Register'!G12:G87,"Not Started") | F7: =COUNTIFS('Feature Register'!L12:L87,A7,'Feature Register'!E12:E87,"P1*",'Feature Register'!G12:G87,"<>Completed")
A8: Backend Lead | B8: =COUNTIF('Feature Register'!L12:L87,A8) | C8: =COUNTIFS('Feature Register'!L12:L87,A8,'Feature Register'!G12:G87,"Completed") | D8: =COUNTIFS('Feature Register'!L12:L87,A8,'Feature Register'!G12:G87,"In Progress") | E8: =COUNTIFS('Feature Register'!L12:L87,A8,'Feature Register'!G12:G87,"Not Started") | F8: =COUNTIFS('Feature Register'!L12:L87,A8,'Feature Register'!E12:E87,"P1*",'Feature Register'!G12:G87,"<>Completed")
A9: Full Stack Developer | B9: =COUNTIF('Feature Register'!L12:L87,A9) | C9: =COUNTIFS('Feature Register'!L12:L87,A9,'Feature Register'!G12:G87,"Completed") | D9: =COUNTIFS('Feature Register'!L12:L87,A9,'Feature Register'!G12:G87,"In Progress") | E9: =COUNTIFS('Feature Register'!L12:L87,A9,'Feature Register'!G12:G87,"Not Started") | F9: =COUNTIFS('Feature Register'!L12:L87,A9,'Feature Register'!E12:E87,"P1*",'Feature Register'!G12:G87,"<>Completed")
A10: QA Lead | B10: =COUNTIF('Feature Register'!L12:L87,A10) | C10: =COUNTIFS('Feature Register'!L12:L87,A10,'Feature Register'!G12:G87,"Completed") | D10: =COUNTIFS('Feature Register'!L12:L87,A10,'Feature Register'!G12:G87,"In Progress") | E10: =COUNTIFS('Feature Register'!L12:L87,A10,'Feature Register'!G12:G87,"Not Started") | F10: =COUNTIFS('Feature Register'!L12:L87,A10,'Feature Register'!E12:E87,"P1*",'Feature Register'!G12:G87,"<>Completed")
A11: DevOps / SRE | B11: =COUNTIF('Feature Register'!L12:L87,A11) | C11: =COUNTIFS('Feature Register'!L12:L87,A11,'Feature Register'!G12:G87,"Completed") | D11: =COUNTIFS('Feature Register'!L12:L87,A11,'Feature Register'!G12:G87,"In Progress") | E11: =COUNTIFS('Feature Register'!L12:L87,A11,'Feature Register'!G12:G87,"Not Started") | F11: =COUNTIFS('Feature Register'!L12:L87,A11,'Feature Register'!E12:E87,"P1*",'Feature Register'!G12:G87,"<>Completed")
A12: Security Lead | B12: =COUNTIF('Feature Register'!L12:L87,A12) | C12: =COUNTIFS('Feature Register'!L12:L87,A12,'Feature Register'!G12:G87,"Completed") | D12: =COUNTIFS('Feature Register'!L12:L87,A12,'Feature Register'!G12:G87,"In Progress") | E12: =COUNTIFS('Feature Register'!L12:L87,A12,'Feature Register'!G12:G87,"Not Started") | F12: =COUNTIFS('Feature Register'!L12:L87,A12,'Feature Register'!E12:E87,"P1*",'Feature Register'!G12:G87,"<>Completed")
A13: UI/UX Designer | B13: =COUNTIF('Feature Register'!L12:L87,A13) | C13: =COUNTIFS('Feature Register'!L12:L87,A13,'Feature Register'!G12:G87,"Completed") | D13: =COUNTIFS('Feature Register'!L12:L87,A13,'Feature Register'!G12:G87,"In Progress") | E13: =COUNTIFS('Feature Register'!L12:L87,A13,'Feature Register'!G12:G87,"Not Started") | F13: =COUNTIFS('Feature Register'!L12:L87,A13,'Feature Register'!E12:E87,"P1*",'Feature Register'!G12:G87,"<>Completed")
A14: Integrations Lead | B14: =COUNTIF('Feature Register'!L12:L87,A14) | C14: =COUNTIFS('Feature Register'!L12:L87,A14,'Feature Register'!G12:G87,"Completed") | D14: =COUNTIFS('Feature Register'!L12:L87,A14,'Feature Register'!G12:G87,"In Progress") | E14: =COUNTIFS('Feature Register'!L12:L87,A14,'Feature Register'!G12:G87,"Not Started") | F14: =COUNTIFS('Feature Register'!L12:L87,A14,'Feature Register'!E12:E87,"P1*",'Feature Register'!G12:G87,"<>Completed")
A15: AI / ML Engineer | B15: =COUNTIF('Feature Register'!L12:L87,A15) | C15: =COUNTIFS('Feature Register'!L12:L87,A15,'Feature Register'!G12:G87,"Completed") | D15: =COUNTIFS('Feature Register'!L12:L87,A15,'Feature Register'!G12:G87,"In Progress") | E15: =COUNTIFS('Feature Register'!L12:L87,A15,'Feature Register'!G12:G87,"Not Started") | F15: =COUNTIFS('Feature Register'!L12:L87,A15,'Feature Register'!E12:E87,"P1*",'Feature Register'!G12:G87,"<>Completed")

Sheet Definitions
A1: Column & status definitions
A3: Field | B3: Definition
A4: Feature ID | B4: Unique reference (FTR-xxx). Used in dependencies.
A5: Module | B5: Product area: Platform, Contributor, Enterprise, Mentor, Admin, Backend.
A6: Overall Status | B6: Not Started → In Progress → Completed. Also: On Hold, Cancelled, Deferred.
A7: Frontend / Backend Status | B7: Delivery layer status. Use N/A when not applicable (e.g. backend-only).
A8: % Complete | B8: Auto-calculated from overall + FE/BE status.
A9: RAG | B9: Auto: Green (on track), Amber (attention), Red (blocked/overdue risk), Grey (deferred).
A10: Assigned To | B10: Person doing the work (developer / lead).
A11: Accountable (EM) | B11: Manager accountable for delivery sign-off.
A12: Planned Start / End | B12: Baseline schedule dates.
A13: Actual End | B13: Fill when Overall Status = Completed.
A14: Dependency ID | B14: Feature ID that must complete first.
A15: Remarks | B15: Blockers, decisions, links to PRD / ticket.
